ddnet_maploader/__init__.py
ddnet_maploader/__version__.py
ddnet_maploader/cbindings.py
ddnet_maploader/ddnet_maploader.py
ddnet_maploader-1.0.0.dist-info/licenses/LICENSE
examples/load_map.py
ddnet_maploader-1.0.0.dist-info/METADATA
ddnet_maploader-1.0.0.dist-info/WHEEL
ddnet_maploader-1.0.0.dist-info/top_level.txt
ddnet_maploader-1.0.0.dist-info/RECORD
