Metadata-Version: 2.4
Name: ddnet_maploader
Version: 1.0.0
Summary: python bindings for ddnet map loader
Home-page: https://github.com/ChillerDragon/ddnet_maploader_py
Author: ChillerDragon
Author-email: chillerdragon@gmail.com
License: BSD-2.0
Project-URL: Bug Tracker, https://github.com/ChillerDragon/ddnet_maploader_py/issues
Project-URL: repository, https://github.com/ChillerDragon/ddnet_maploader_py
Classifier: Development Status :: 3 - Alpha
Classifier: Programming Language :: Python :: 3
Classifier: License :: OSI Approved :: BSD License
Classifier: Operating System :: OS Independent
License-File: LICENSE
Dynamic: license-file
